{
    "epochs": 30,
    "batch_size": 64,
    "validation_split": 0,
    "verbose": 1,
    "sequence_size": 300,
    "padding_type": "pre",
    "bow_num_words": 3000,
    "active-model": "app_data\\model_data\\saved_models\\ds_base_100d_100k_v1\\master-l2-vx_1_drop0.06\\adam_0.01\\model.h5",
    "log-dir": "app_data\\model_data\\logs",
    "save-dir": "app_data\\model_data\\saved_models",
    "checkpoint-dir": "app_data\\model_data\\model_checkpoints",
    "transition-dir": "app_data\\model_data\\model_transition",
    "binaries-dir": "app_data\\model_data\\model_binaries",
    "raw-dataset-dir":"app_data\\raw-dataset\\aclImdb",
    "emb_dir": "app_data\\embeddings",
    "save_model_plots": true,
    "log_device_placement": false,
    "generate_summary": true,
    "nlp_lowercase": true,
    "nlp_apply_lemma": true,
    "nlp_simplify_entities": false,
    "nlp_remove_stop_words": true,
    "nlp_cleanse_text": true,
    "nlp_remove_verb_contractions":true,
    "nlp_replace_extended_chars":true,
    "nlp_model_name": "en_core_web_sm",
    "embedding-lookup-dir": "app_data\\embedding-lookups",
    "master-model-dir": "app_data\\master_models",
    "glove-embedding-lookup-dir": "embeddings",
    "vocab_size": 300000,
    "embedding-dir": "embeddings\\glove.6B\\",
    "active-embedding-lookup-dir": "embedding-lookups\\100d_300k",
    "processed-data":"app_data\\processed-datasets\\data.json",
    "processed-data-dir":"app_data\\processed-datasets"
}